moonpy/__init__.py
moonpy/errors.py
moonpy/stats.py
moonpy/util.py
moonpy-0.1.1.dist-info/LICENSE
moonpy-0.1.1.dist-info/WHEEL
moonpy-0.1.1.dist-info/METADATA
moonpy-0.1.1.dist-info/RECORD
